sol_transfer_sdk/__init__.py
sol_transfer_sdk/api.cp312-win_amd64.pyd
sol_transfer_sdk/api.cpython-312-x86_64-linux-gnu.so
sol_transfer_sdk-0.0.1.dist-info/METADATA
sol_transfer_sdk-0.0.1.dist-info/WHEEL
sol_transfer_sdk-0.0.1.dist-info/RECORD
