Metadata-Version: 2.3
Name: sol-transfer-sdk
Version: 0.0.1
Summary: 
Author: sol_dev
Author-email: 888888888@gmail.com
Requires-Python: >=3.12
Classifier: Programming Language :: Python :: 3
Classifier: Programming Language :: Python :: 3.12
Classifier: Programming Language :: Python :: 3.13
Requires-Dist: cython (==3.0.12)
Requires-Dist: pytoniq (==0.1.40)
Requires-Dist: retrying (==1.3.4)
Requires-Dist: setuptools (==75.1.0)
Requires-Dist: solana (==0.36.1)
Requires-Dist: solders (==0.23.0)
